{"cameraMode":{"drawMode":0,"name":"Shaded","section":"Shading Mode"},"sceneLighting":false,"audioPlay":false,"sceneViewState":{"m_AlwaysRefresh":false,"showFog":true,"showSkybox":false,"showFlares":true,"showImageEffects":true,"showParticleSystems":true,"showVisualEffectGraphs":true,"m_FxEnabled":true},"in2DMode":false,"pivot":{"x":-0.04072856903076172,"y":0.4065755009651184,"z":0.0},"rotation":{"x":-0.4488661587238312,"y":-0.0963747426867485,"z":0.04861452430486679,"w":-0.8873441219329834},"size":0.5962284207344055,"orthographic":false}