{"cameraMode":{"drawMode":0,"name":"Shaded","section":"Shading Mode"},"sceneLighting":false,"audioPlay":false,"sceneViewState":{"m_AlwaysRefresh":false,"showFog":true,"showSkybox":false,"showFlares":true,"showImageEffects":true,"showParticleSystems":true,"showVisualEffectGraphs":true,"m_FxEnabled":true},"in2DMode":false,"pivot":{"x":-0.07127682864665985,"y":1.855771780014038,"z":3.5747509002685549},"rotation":{"x":-0.03472139313817024,"y":-0.9479634761810303,"z":0.11178292334079743,"w":-0.29641178250312807},"size":2.234926462173462,"orthographic":false}